[
  {
    "intent": "ration_card",
    "input": "naku ration card kavali\n",
    "letter": "గౌరవ తహశీల్దార్ గారికి,\n[Mandal Name] మండలం,\n[District Name] జిల్లా.\n\nవిషయం: కొత్త రేషన్ కార్డు కోసం దరఖాస్తు\n\nగౌరవనీయులైన సర్/మేడం,\n\nనేను, Applicant, [Address] నివాసి, మా కుటుంబానికి కొత్త రేషన్ కార్డు జారీ చేయవలసినదిగా మీ ద్వారా ఈ దరఖాస్తును సమర్పిస్తున్నాను.\n\nకుటుంబ వివరాలు:\nకుటుంబ ముఖ్యస్థుడు: Applicant\nచిరునామా: [Address]\nకుటుంబ సభ్యులు: [Number of Family Members]\nమొత్తం కుటుంబ ఆదాయం: రూ. [Annual Income] సంవత్సరానికి\n\nజతచేసిన పత్రాలు:\n1. చిరునామా ధృవీకరణ\n2. ఆదాయ ధృవీకరణ పత్రం\n3. కుటుంబ ఫోటో\n4. అన్ని కుటుంబ సభ్యుల ఆధార్ కార్డులు\n\nమీ ద్వారా నా దరఖాస్తును పరిశీలించి త్వరలో రేషన్ కార్డు జారీ చేయవలసినదిగా వినతిచేస్తున్నాను.\n\nధన్యవాదాలతో,\nమీ విధేయుడు,\nApplicant\nPhone: Not provided",
    "language": "telugu",
    "timestamp": "2025-08-02 11:48:43"
  },
  {
    "intent": "ration_card",
    "input": "naku ration card kavali\n",
    "letter": "గౌరవ తహశీల్దార్ గారికి,\n[Mandal Name] మండలం,\n[District Name] జిల్లా.\n\nవిషయం: కొత్త రేషన్ కార్డు కోసం దరఖాస్తు\n\nగౌరవనీయులైన సర్/మేడం,\n\nనేను, Applicant, [Address] నివాసి, మా కుటుంబానికి కొత్త రేషన్ కార్డు జారీ చేయవలసినదిగా మీ ద్వారా ఈ దరఖాస్తును సమర్పిస్తున్నాను.\n\nకుటుంబ వివరాలు:\nకుటుంబ ముఖ్యస్థుడు: Applicant\nచిరునామా: [Address]\nకుటుంబ సభ్యులు: [Number of Family Members]\nమొత్తం కుటుంబ ఆదాయం: రూ. [Annual Income] సంవత్సరానికి\n\nజతచేసిన పత్రాలు:\n1. చిరునామా ధృవీకరణ\n2. ఆదాయ ధృవీకరణ పత్రం\n3. కుటుంబ ఫోటో\n4. అన్ని కుటుంబ సభ్యుల ఆధార్ కార్డులు\n\nమీ ద్వారా నా దరఖాస్తును పరిశీలించి త్వరలో రేషన్ కార్డు జారీ చేయవలసినదిగా వినతిచేస్తున్నాను.\n\nధన్యవాదాలతో,\nమీ విధేయుడు,\nApplicant\nPhone: Not provided",
    "language": "telugu",
    "timestamp": "2025-08-02 11:48:45"
  },
  {
    "intent": "income_certificate",
    "input": "naku income kavali",
    "letter": "To,\nThe Tahsildar,\n[Mandal Name] Mandal,\n[District Name] District.\n\nSubject: Application for Income Certificate\n\nRespected Sir/Madam,\n\nI, Applicant, resident of [Address], hereby submit this application requesting you to issue an income certificate for my family.\n\nPersonal Details:\nName: Applicant\nAddress: [Address]\nOccupation: [Occupation]\nAnnual Income: Rs. [Annual Income]\n\nPurpose of Certificate: [Purpose]\n\nDocuments attached:\n1. Salary certificate/Income proof\n2. Address proof\n3. Aadhaar card\n\nI kindly request you to process my application and issue the income certificate at the earliest.\n\nThanking you,\nYours faithfully,\nApplicant\nPhone: Not provided",
    "language": "english",
    "timestamp": "2025-08-02 12:42:21"
  },
  {
    "intent": "general",
    "input": "naku leave letter kavali",
    "letter": "Dear Sir/Madam,\n\nnaku leave letter kavali\n\nSincerely,\nApplicant",
    "language": "english",
    "timestamp": "2025-08-02 12:54:21"
  },
  {
    "intent": "ration_card",
    "input": "naku ration card kavali",
    "letter": "To,\nThe Tahsildar,\n[Mandal Name] Mandal,\n[District Name] District.\n\nSubject: Application for New Ration Card\n\nRespected Sir/Madam,\n\nI, Applicant, resident of [Address], hereby submit this application requesting you to issue a new ration card for my family.\n\nFamily Details:\nHead of Family: Applicant\nAddress: [Address]\nFamily Members: [Number of Family Members]\nTotal Family Income: Rs. [Annual Income] per annum\n\nDocuments attached:\n1. Address proof\n2. Income certificate\n3. Family photo\n4. Aadhaar cards of all family members\n\nI kindly request you to process my application and issue the ration card at the earliest.\n\nThanking you,\nYours faithfully,\nApplicant\nPhone: Not provided",
    "language": "english",
    "timestamp": "2025-08-02 12:54:44"
  },
  {
    "intent": "income_certificate",
    "input": "naku income kavali",
    "letter": "గౌరవ తహశీల్దార్ గారికి,\n[Mandal Name] మండలం,\n[District Name] జిల్లా.\n\nవిషయం: ఆదాయ ధృవీకరణ పత్రం కోసం దరఖాస్తు\n\nగౌరవనీయులైన సర్/మేడం,\n\nనేను, Applicant, [Address] నివాసి, మా కుటుంబానికి ఆదాయ ధృవీకరణ పత్రం జారీ చేయవలసినదిగా మీ ద్వారా ఈ దరఖాస్తును సమర్పిస్తున్నాను.\n\nవ్యక్తిగత వివరాలు:\nపేరు: Applicant\nచిరునామా: [Address]\nవృత్తి: [Occupation]\nవార్షిక ఆదాయం: రూ. [Annual Income]\n\nపత్రం ఉపయోగం: [Purpose]\n\nజతచేసిన పత్రాలు:\n1. జీతం ధృవీకరణ/ఆదాయ ధృవీకరణ\n2. చిరునామా ధృవీకరణ\n3. ఆధార్ కార్డు\n\nమీ ద్వారా నా దరఖాస్తును పరిశీలించి త్వరలో ఆదాయ ధృవీకరణ పత్రం జారీ చేయవలసినదిగా వినతిచేస్తున్నాను.\n\nధన్యవాదాలతో,\nమీ విధేయుడు,\nApplicant\nPhone: Not provided",
    "language": "telugu",
    "timestamp": "2025-08-02 23:22:26"
  },
  {
    "intent": "income_certificate",
    "input": "naku income certficate kavali",
    "letter": "గౌరవ తహశీల్దార్ గారికి,\n[Mandal Name] మండలం,\n[District Name] జిల్లా.\n\nవిషయం: ఆదాయ ధృవీకరణ పత్రం కోసం దరఖాస్తు\n\nగౌరవనీయులైన సర్/మేడం,\n\nనేను, Applicant, [Address] నివాసి, మా కుటుంబానికి ఆదాయ ధృవీకరణ పత్రం జారీ చేయవలసినదిగా మీ ద్వారా ఈ దరఖాస్తును సమర్పిస్తున్నాను.\n\nవ్యక్తిగత వివరాలు:\nపేరు: Applicant\nచిరునామా: [Address]\nవృత్తి: [Occupation]\nవార్షిక ఆదాయం: రూ. [Annual Income]\n\nపత్రం ఉపయోగం: [Purpose]\n\nజతచేసిన పత్రాలు:\n1. జీతం ధృవీకరణ/ఆదాయ ధృవీకరణ\n2. చిరునామా ధృవీకరణ\n3. ఆధార్ కార్డు\n\nమీ ద్వారా నా దరఖాస్తును పరిశీలించి త్వరలో ఆదాయ ధృవీకరణ పత్రం జారీ చేయవలసినదిగా వినతిచేస్తున్నాను.\n\nధన్యవాదాలతో,\nమీ విధేయుడు,\nApplicant\nPhone: Not provided",
    "language": "telugu",
    "timestamp": "2025-08-05 20:48:34"
  },
  {
    "intent": "general",
    "input": "naku voter id card kavali\n",
    "letter": "Dear Sir/Madam,\n\nnaku voter id card kavali\n\n\nSincerely,\nApplicant",
    "language": "english",
    "timestamp": "2025-08-05 20:49:26"
  },
  {
    "intent": "general",
    "input": "naku  leave letter kava naku corono vachindi\n",
    "letter": "గౌరవ తహశీల్దార్ గారికి,\n\nnaku  leave letter kava naku corono vachindi\n\n\nధన్యవాదాలతో,\nమీ విధేయుడు",
    "language": "telugu",
    "timestamp": "2025-08-05 22:07:23"
  }
]